normal_api/__init__.py
normal_api/classes.py
normal_api/client.py
normal_api/errors.py
normal_api/http.py
normal_api.py-1.0.0.dist-info/LICENSE
normal_api.py-1.0.0.dist-info/METADATA
normal_api.py-1.0.0.dist-info/WHEEL
normal_api.py-1.0.0.dist-info/top_level.txt
normal_api.py-1.0.0.dist-info/RECORD
