Metadata-Version: 2.1
Name: normal-api.py
Version: 1.0.0
Summary: An Easy-To-Use Wrapper for the Normal API
Home-page: https://github.com/Soheab/normal_api.py
Author: Soheab_
License: MIT
Download-URL: https://github.com/Soheab/normal_api.py/archive/v1.0.0.tar.gz
Project-URL: Discord, https://discord.gg/FyQ3CnmnQK
Project-URL: Documentation, https://github.com/Soheab/normal_api.py/blob/main/docs.md
Keywords: normal_api,discord,api,wrapper,memes,image,discord.py
Platform: UNKNOWN
Requires-Python: >=3.6
Requires-Dist: aiohttp
